api_2fa_fb/__init__.py
api_2fa_fb-1.0.0.dist-info/LICENSE
api_2fa_fb-1.0.0.dist-info/METADATA
api_2fa_fb-1.0.0.dist-info/WHEEL
api_2fa_fb-1.0.0.dist-info/top_level.txt
api_2fa_fb-1.0.0.dist-info/RECORD
