Metadata-Version: 2.2
Name: api_2fa_fb
Version: 1.0.0
Summary: A Python package for fetching Facebook 2FA OTP
Author: Nguyễn Minh Đức
Author-email: dancntt7@gmail.com
Classifier: Programming Language :: Python :: 3
Classifier: License :: OSI Approved :: MIT License
Classifier: Operating System :: OS Independent
Requires-Python: >=3.10
License-File: LICENSE
Requires-Dist: requests
Dynamic: author
Dynamic: author-email
Dynamic: classifier
Dynamic: description
Dynamic: description-content-type
Dynamic: requires-dist
Dynamic: requires-python
Dynamic: summary
